hestia_converters-0.0.2.data/scripts/hestia-convert
hestia_earth/__init__.py
hestia_earth/converters/__init__.py
hestia_earth/converters/base/__init__.py
hestia_earth/converters/base/portable_tools.py
hestia_earth/converters/base/RosettaFlow/__init__.py
hestia_earth/converters/base/RosettaFlow/file_shemas.py
hestia_earth/converters/base/RosettaFlow/file_validation.py
hestia_earth/converters/base/RosettaFlow/tools/__init__.py
hestia_earth/converters/base/RosettaFlow/tools/utils.py
hestia_earth/converters/base/converter/__init__.py
hestia_earth/converters/base/converter/helpers.py
hestia_earth/converters/base/converter/utils.py
hestia_earth/converters/base/pydantic_models/__init__.py
hestia_earth/converters/base/pydantic_models/hestia/__init__.py
hestia_earth/converters/base/pydantic_models/hestia/api_utils.py
hestia_earth/converters/base/pydantic_models/hestia/hestia_file_tools.py
hestia_earth/converters/base/pydantic_models/hestia/hestia_schema_tools.py
hestia_earth/converters/base/pydantic_models/hestia/hestia_schema_utils.py
hestia_earth/converters/simapro/__init__.py
hestia_earth/converters/simapro/ecoinvent_api.py
hestia_earth/converters/simapro/log.py
hestia_earth/converters/simapro/hestia_to_simapro/__init__.py
hestia_earth/converters/simapro/hestia_to_simapro/convert.py
hestia_earth/converters/simapro/pydantic_models/__init__.py
hestia_earth/converters/simapro/pydantic_models/schema_enums.py
hestia_earth/converters/simapro/pydantic_models/util.py
hestia_earth/converters/simapro/rosetta_flow/__init__.py
hestia_earth/converters/simapro/rosetta_flow/helpers.py
scripts/simapro/__init__.py
scripts/simapro/load_file.py
tests/converters/__init__.py
tests/converters/simapro/__init__.py
tests/converters/simapro/test_hestia_to_simapro.py
tests/converters/simapro/pydantic_models/__init__.py
tests/converters/simapro/pydantic_models/test_util.py
hestia_converters-0.0.2.dist-info/LICENSE
hestia_converters-0.0.2.dist-info/METADATA
hestia_converters-0.0.2.dist-info/WHEEL
hestia_converters-0.0.2.dist-info/top_level.txt
hestia_converters-0.0.2.dist-info/RECORD
