Metadata-Version: 2.1
Name: hestia-converters
Version: 0.0.2
Summary: HESTIA's set of file converters
Home-page: https://gitlab.com/hestia-earth/hestia-convert-base
Author: @ToffeeLabs
Author-email: community@hestia.earth
License: MIT
Classifier: Programming Language :: Python :: 3.9
Requires-Python: >=3.9
License-File: LICENSE
Requires-Dist: Werkzeug
Requires-Dist: pydantic (==2.*)
Requires-Dist: pydantic-core (==2.*)
Requires-Dist: hestia-earth-schema (>=33.6.0)
Requires-Dist: hestia-earth-utils
Requires-Dist: python-dateutil
Requires-Dist: numpy
Requires-Dist: pandas
Requires-Dist: setuptools
Provides-Extra: simapro
Requires-Dist: hestia-earth-models (>=0.74.8) ; extra == 'simapro'
Requires-Dist: hestia-earth-utils ; extra == 'simapro'
Requires-Dist: bw-simapro-csv (==0.4.2) ; extra == 'simapro'
Requires-Dist: pydantic (==2.*) ; extra == 'simapro'
Requires-Dist: pydantic[email] ; extra == 'simapro'
Requires-Dist: requests ; extra == 'simapro'
